gitsweep/__init__.py
gitsweep/base.py
gitsweep/cli.py
gitsweep/deleter.py
gitsweep/entrypoints.py
gitsweep/inspector.py
gitsweep/scripts/__init__.py
gitsweep/scripts/test.py
git_sweep_merged_and_stale-1.0b1.dist-info/LICENSE.txt
git_sweep_merged_and_stale-1.0b1.dist-info/METADATA
git_sweep_merged_and_stale-1.0b1.dist-info/WHEEL
git_sweep_merged_and_stale-1.0b1.dist-info/entry_points.txt
git_sweep_merged_and_stale-1.0b1.dist-info/top_level.txt
git_sweep_merged_and_stale-1.0b1.dist-info/RECORD
