Metadata-Version: 2.1
Name: git-sweep-merged-and-stale
Version: 1.0b1
Summary: Clean up branches from your Git remotes
Home-page: http://rod.codes
Author: Rodney Hawkins
Author-email: rodneyhawkins@gmail.com
License: MIT
Keywords: git maintenance branches merge stale
Platform: UNKNOWN
Classifier: Development Status :: 4 - Beta
Classifier: Environment :: Console
Classifier: License :: OSI Approved :: MIT License
Classifier: Intended Audience :: Developers
Classifier: Natural Language :: English
Classifier: Operating System :: POSIX
Classifier: Programming Language :: Python :: 3.7
Classifier: Topic :: Software Development :: Quality Assurance
Classifier: Topic :: Software Development :: Version Control
Classifier: Topic :: Text Processing
Requires-Dist: GitPython (>=3.1)
